toolcli/__init__.py
toolcli/__main__.py
toolcli/capture_utils.py
toolcli/file_edit_utils.py
toolcli/file_validate_utils.py
toolcli/input_utils.py
toolcli/py.typed
toolcli/spec.py
toolcli/terminal_utils.py
toolcli/command_utils/__init__.py
toolcli/command_utils/execution.py
toolcli/command_utils/output_utils.py
toolcli/command_utils/plugin_utils.py
toolcli/command_utils/dev_utils/__init__.py
toolcli/command_utils/dev_utils/cli_typing.py
toolcli/command_utils/help_utils/__init__.py
toolcli/command_utils/help_utils/root_command_help.py
toolcli/command_utils/help_utils/subcommand_help.py
toolcli/command_utils/parsing/__init__.py
toolcli/command_utils/parsing/arg_parsing.py
toolcli/command_utils/parsing/command_parsing.py
toolcli/command_utils/parsing/index_parsing.py
toolcli/command_utils/standard_subcommands/__init__.py
toolcli/command_utils/standard_subcommands/cd_command.py
toolcli/command_utils/standard_subcommands/help_command.py
toolcli/command_utils/standard_subcommands/record_help_command.py
toolcli/command_utils/standard_subcommands/version_command.py
toolcli/command_utils/standard_subcommands/cli/__init__.py
toolcli/command_utils/standard_subcommands/cli/annotate_command.py
toolcli/command_utils/standard_subcommands/cli/config_command.py
toolcli/command_utils/standard_subcommands/cli/edit_command.py
toolcli/command_utils/standard_subcommands/cli/index_command.py
toolcli/command_utils/standard_subcommands/cli/spec_command.py
toolcli/command_utils/standard_subcommands/cli/theme_command.py
toolcli-0.6.5.dist-info/LICENSE
toolcli-0.6.5.dist-info/WHEEL
toolcli-0.6.5.dist-info/METADATA
toolcli-0.6.5.dist-info/RECORD
