Metadata-Version: 2.1
Name: toolcli
Version: 0.6.5
Summary: toolcli makes it easy to create structured hierarchical cli tools
Requires-Python: >=3.7
Requires-Dist: rich>=12.1.0
Requires-Dist: typing_extensions>=0.4.0
Requires-Dist: ipdb>=0.13.1 ; extra == "full"
Provides-Extra: full
